vulnebify/__init__.py
vulnebify/cli.py
vulnebify/client.py
vulnebify/errors.py
vulnebify/models.py
vulnebify/output.py
vulnebify-1.0.4.dist-info/LICENSE
vulnebify-1.0.4.dist-info/METADATA
vulnebify-1.0.4.dist-info/WHEEL
vulnebify-1.0.4.dist-info/entry_points.txt
vulnebify-1.0.4.dist-info/top_level.txt
vulnebify-1.0.4.dist-info/RECORD
