Metadata-Version: 2.1
Name: vulnebify
Version: 1.0.4
Summary: Python library for the Vulnebify API. Run scans, inspect hosts/domains, and fetch results with real-time updates and JSON output.
Home-page: https://github.com/vulnebify/vulnebify-python
Author: Alex @ Vulnebify
Author-email: contact.pypi@vulnebify.com
Classifier: Programming Language :: Python :: 3
Classifier: License :: OSI Approved :: MIT License
Classifier: Operating System :: OS Independent
Requires-Python: >=3.6
License-File: LICENSE
Requires-Dist: requests==2.32.3
Requires-Dist: pydantic==2.11.2
